<?xml version="1.0" encoding="utf-8" ?><dwsync><file name="index.html" server="Macintosh HD/Applications/MAMP/htdocs/netseclab/" local="3404811158" remote="11994745750" /><file name="sqlite_driver.php" server="Macintosh HD/Applications/MAMP/htdocs/netseclab/" local="3432543512" remote="12022478104" /><file name="sqlite_forge.php" server="Macintosh HD/Applications/MAMP/htdocs/netseclab/" local="3432543512" remote="12022478104" /><file name="sqlite_result.php" server="Macintosh HD/Applications/MAMP/htdocs/netseclab/" local="3432543512" remote="12022478104" /><file name="sqlite_utility.php" server="Macintosh HD/Applications/MAMP/htdocs/netseclab/" local="3432543512" remote="12022478104" /><file name="index.html" server="netseclab.gatech.edu//httpdocs/" local="3442489968" remote="20622359152" /><file name="sqlite_driver.php" server="netseclab.gatech.edu//httpdocs/" local="3442489968" remote="20622359152" /><file name="sqlite_forge.php" server="netseclab.gatech.edu//httpdocs/" local="3442489968" remote="20622359152" /><file name="sqlite_result.php" server="netseclab.gatech.edu//httpdocs/" local="3442489968" remote="20622359152" /><file name="sqlite_utility.php" server="netseclab.gatech.edu//httpdocs/" local="3442489968" remote="20622359152" /></dwsync>